dopus/__init__.py
dopus/core/__init__.py
dopus/core/agent.py
dopus/core/convo.py
dopus/core/provider.py
dopus/core/tool.py
dopus/core/tool_registry.py
dopus/core/tool_runner.py
dopus/provider/__init__.py
dopus/provider/anthropic.py
dopus/provider/groq.py
dopus/provider/open_ai.py
dopus/test/__init__.py
dopus/test/dopus_test.py
dopus/util.py
dopus-202409201709.dist-info/LICENSE
dopus-202409201709.dist-info/METADATA
dopus-202409201709.dist-info/WHEEL
dopus-202409201709.dist-info/entry_points.txt
dopus-202409201709.dist-info/RECORD
