Metadata-Version: 2.1
Name: dopus
Version: 202409201709
Summary: A lightweight tool-first framework for AI agent application development
License: MIT
Author: Mike Ashcroft
Requires-Python: >=3.12,<4.0
Classifier: License :: OSI Approved :: MIT License
Classifier: Programming Language :: Python :: 3
Classifier: Programming Language :: Python :: 3.12
Requires-Dist: pydantic (>=2.9.2,<3.0.0)
